README.md
setup.cfg
setup.py
Watermarkd/Watermarkd.py
Watermarkd/__init__.py
Watermarkd.egg-info/PKG-INFO
Watermarkd.egg-info/SOURCES.txt
Watermarkd.egg-info/dependency_links.txt
Watermarkd.egg-info/requires.txt
Watermarkd.egg-info/top_level.txt