Metadata-Version: 2.1
Name: Watermarkd
Version: 0.7.2.1
Summary: A friendly watermarking tool with optional GUI component.
Home-page: https://holypython.com/
Author: holypython.com
Author-email: watermarkd@holypython.com
License: Apache-2.0
Download-URL: https://github.com/holypython/Watermarkd/archive/0.7.2.1.tar.gz
Keywords: watermarking,image processing,watermark,photography,copyrights,holypython,batch watermark,holypython.com
Platform: UNKNOWN
Classifier: Development Status :: 3 - Alpha
Classifier: Intended Audience :: Developers
Classifier: Intended Audience :: Education
Classifier: Intended Audience :: End Users/Desktop
Classifier: Programming Language :: Python :: 3
Classifier: License :: OSI Approved :: Apache Software License
Classifier: Operating System :: OS Independent
Requires-Python: >=3.6
